{
  "required": true,
  "minVersion": "0.8",
  "package": "dev.yurisuika.raised.mixin",
  "refmap": "raised.refmap.json",
  "compatibilityLevel": "JAVA_17",
  "mixins": [
    "mods.ForgeMixin$OverlayRegistryMixin"
  ],
  "client": [
    "client.OptionInvoker",
    "client.gui.GuiMixin$Hotbar$Pre",
    "client.gui.GuiMixin$Other$Post",
    "client.gui.GuiMixin$Other$Pre",
    "client.gui.components.AbstractSelectionListMixin",
    "client.gui.components.AbstractWidgetMixin",
    "client.gui.components.ChatComponentMixin$Chat$Pre",
    "client.gui.components.toasts.ToastComponentMixin$Toasts$Pre"
  ],
  "injectors": {
    "defaultRequire": 1
  }
}